{"lastUsed":1693314640623,"path":"C:\/Users\/jay-pc\/Selenium TTS 6-30 to 7-30","projectCount":1,"recentFiles":[{"path":"\/Core JAVA\/src\/basic","parentWorkspace":"C:\/Users\/jay-pc\/Selenium TTS 6-30 to 7-30","name":"P000_Second_Class.java","lastModified":1693057949674,"locationURI":"file:\/C:\/Users\/jay-pc\/Selenium%20TTS%206-30%20to%207-30\/Core%20JAVA\/src\/basic\/P000_Second_Class.java"},{"path":"\/Core JAVA\/src\/basic","parentWorkspace":"C:\/Users\/jay-pc\/Selenium TTS 6-30 to 7-30","name":"P001_DataType.java","lastModified":1693058687996,"locationURI":"file:\/C:\/Users\/jay-pc\/Selenium%20TTS%206-30%20to%207-30\/Core%20JAVA\/src\/basic\/P001_DataType.java"}]}